{
   "results" : [
      {
         "address_components" : [
            {
               "long_name" : "12876",
               "short_name" : "12876",
               "types" : [ "street_number" ]
            },
            {
               "long_name" : "Saratoga Sunnyvale Road",
               "short_name" : "Saratoga Sunnyvale Rd",
               "types" : [ "route" ]
            },
            {
               "long_name" : "Saratoga",
               "short_name" : "Saratoga",
               "types" : [ "locality", "political" ]
            },
            {
               "long_name" : "Santa Clara County",
               "short_name" : "Santa Clara County",
               "types" : [ "administrative_area_level_2", "political" ]
            },
            {
               "long_name" : "California",
               "short_name" : "CA",
               "types" : [ "administrative_area_level_1", "political" ]
            },
            {
               "long_name" : "United States",
               "short_name" : "US",
               "types" : [ "country", "political" ]
            },
            {
               "long_name" : "95070",
               "short_name" : "95070",
               "types" : [ "postal_code" ]
            }
         ],
         "formatted_address" : "12876 Saratoga Sunnyvale Rd, Saratoga, CA 95070, USA",
         "geometry" : {
            "location" : {
               "lat" : 37.2812192,
               "lng" : -122.03125
            },
            "location_type" : "ROOFTOP",
            "viewport" : {
               "northeast" : {
                  "lat" : 37.2825681802915,
                  "lng" : -122.0299010197085
               },
               "southwest" : {
                  "lat" : 37.2798702197085,
                  "lng" : -122.0325989802915
               }
            }
         },
         "place_id" : "ChIJOZtpQCy1j4ARil4EGcVuBWk",
         "plus_code" : {
            "compound_code" : "7XJ9+FF Saratoga, California, United States",
            "global_code" : "849V7XJ9+FF"
         },
         "types" : [
            "establishment",
            "food",
            "grocery_or_supermarket",
            "point_of_interest",
            "store"
         ]
      }
   ],
   "status" : "OK"
}
